pytest_plugin_helpers/__init__.py
pytest_plugin_helpers/plugin.py
pytest_plugin_helpers/tester.py
pytest_plugin_helpers-0.1.0.dist-info/LICENSE
pytest_plugin_helpers-0.1.0.dist-info/METADATA
pytest_plugin_helpers-0.1.0.dist-info/WHEEL
pytest_plugin_helpers-0.1.0.dist-info/entry_points.txt
pytest_plugin_helpers-0.1.0.dist-info/top_level.txt
pytest_plugin_helpers-0.1.0.dist-info/RECORD
