Metadata-Version: 2.1
Name: pytest-plugin-helpers
Version: 0.1.0
Summary: A plugin to help developing and testing other plugins
Home-page: https://gitlab.com/too-many-programmers/pytest-plugin-helpers
Author: Benjamin Rigaud
Author-email: ben.open.source@gmail.com
Maintainer: Benjamin Rigaud
Maintainer-email: ben.open.source@gmail.com
License: MIT
Platform: UNKNOWN
Classifier: Development Status :: 4 - Beta
Classifier: Framework :: Pytest
Classifier: Intended Audience :: Developers
Classifier: Topic :: Software Development :: Testing
Classifier: Programming Language :: Python
Classifier: Programming Language :: Python :: 3
Classifier: Programming Language :: Python :: 3.5
Classifier: Programming Language :: Python :: 3.6
Classifier: Programming Language :: Python :: 3.7
Classifier: Programming Language :: Python :: Implementation :: CPython
Classifier: Programming Language :: Python :: Implementation :: PyPy
Classifier: Operating System :: OS Independent
Classifier: License :: OSI Approved :: MIT License
Requires-Python: >=3.5
Requires-Dist: pytest (>=3.5.0)
Requires-Dist: makefun (>=1.7.0)
